pycoingecko/__init__.py
pycoingecko/coingecko.py
pycoingecko/py.typed
pycoingecko/clients/__init__.py
pycoingecko/clients/demo.py
pycoingecko/clients/onchain.py
pycoingecko/clients/pro.py
pycoingecko/resources/__init__.py
pycoingecko/resources/asset_platforms.py
pycoingecko/resources/categories.py
pycoingecko/resources/coins.py
pycoingecko/resources/companies.py
pycoingecko/resources/contract.py
pycoingecko/resources/derivatives.py
pycoingecko/resources/exchange_rates.py
pycoingecko/resources/exchanges.py
pycoingecko/resources/global_data.py
pycoingecko/resources/ping.py
pycoingecko/resources/search.py
pycoingecko/resources/simple.py
pycoingecko/resources/trending.py
pycoingecko/resources/pro/__init__.py
pycoingecko/resources/pro/coins.py
pycoingecko/resources/pro/exchanges.py
pycoingecko/resources/pro/global_data.py
pycoingecko/resources/pro/key.py
pycoingecko/resources/pro/onchain/__init__.py
pycoingecko/utils/__init__.py
pycoingecko/utils/constants.py
pycoingecko/utils/enums.py
pycoingecko/utils/exceptions.py
pycoingecko/utils/helpers.py
pycoingecko/utils/http.py
pycoingecko/utils/interfaces.py
pycoingecko/utils/types.py
python_coingecko-0.0.3.dist-info/AUTHORS
python_coingecko-0.0.3.dist-info/LICENSE
python_coingecko-0.0.3.dist-info/METADATA
python_coingecko-0.0.3.dist-info/WHEEL
python_coingecko-0.0.3.dist-info/top_level.txt
python_coingecko-0.0.3.dist-info/RECORD
