Metadata-Version: 2.1
Name: python-coingecko
Version: 0.0.3
Summary: Python wrapper for coingecko.com v3 api
Maintainer-email: Nick Kelly <nialexanderke@proton.me>
Project-URL: Homepage, https://github.com/nickatnight/python-coingecko
Project-URL: Issues, https://github.com/nickatnight/python-coingecko/issues
Requires-Python: >=3.11
License-File: LICENSE
License-File: AUTHORS
Requires-Dist: requests ==2.32.3
